lripy/__init__.py
lripy/dr.py
lripy/drcomplete.py
lripy/drhankelapprox.py
lripy/projhankel.py
lripy/projindex.py
lripy/projrast.py
lripy/projrnorm.py
lripy/proxnonconv.py
lripy/proxnonconv_square.py
lripy/proxnormrast.py
lripy/proxnormrast_square.py
lripy-0.0.2.dist-info/METADATA
lripy-0.0.2.dist-info/RECORD
lripy-0.0.2.dist-info/WHEEL
lripy-0.0.2.dist-info/top_level.txt
