Metadata-Version: 2.1
Name: lripy
Version: 0.0.2
Summary: Python implementation for optimization with Low-Rank Inducing Norms
Home-page: http://github.com/LowRankOpt/LRIPy
Author: Christian Grussler
Author-email: christian.grussler@eng.cam.ac.uk
License: GPLv3
Platform: UNKNOWN
Classifier: Programming Language :: Python :: 3
Classifier: Operating System :: OS Independent
